mcp_n8n/__init__.py
mcp_n8n/config.py
mcp_n8n/credential_validator.py
mcp_n8n/event_watcher.py
mcp_n8n/gateway.py
mcp_n8n/logging_config.py
mcp_n8n/backends/__init__.py
mcp_n8n/backends/base.py
mcp_n8n/backends/chora_composer.py
mcp_n8n/backends/coda_mcp.py
mcp_n8n/backends/registry.py
mcp_n8n/cli/__init__.py
mcp_n8n/cli/commands.py
mcp_n8n/cli/main.py
mcp_n8n/mcp/__init__.py
mcp_n8n/memory/__init__.py
mcp_n8n/memory/event_log.py
mcp_n8n/memory/knowledge_graph.py
mcp_n8n/memory/profiles.py
mcp_n8n/memory/trace.py
mcp_n8n/tools/__init__.py
mcp_n8n/tools/event_query.py
mcp_n8n/workflows/__init__.py
mcp_n8n/workflows/__main__.py
mcp_n8n/workflows/daily_report.py
mcp_n8n/workflows/event_router.py
mcp_n8n-0.6.0.dist-info/METADATA
mcp_n8n-0.6.0.dist-info/WHEEL
mcp_n8n-0.6.0.dist-info/entry_points.txt
mcp_n8n-0.6.0.dist-info/licenses/LICENSE
mcp_n8n-0.6.0.dist-info/RECORD
