Metadata-Version: 2.4
Name: mcp-n8n
Version: 0.6.0
Summary: MCP Gateway & Aggregator - Routes artifact creation to Chora Composer and integrates multiple MCP servers
Author-email: Victor Piper <victor@example.com>
License: MIT
License-File: LICENSE
Requires-Python: >=3.12
Requires-Dist: aiohttp>=3.9.0
Requires-Dist: chora-compose>=1.3.0
Requires-Dist: click>=8.0.0
Requires-Dist: fastmcp>=0.3.0
Requires-Dist: pydantic-settings>=2.0.0
Requires-Dist: pydantic>=2.0.0
Requires-Dist: python-dotenv>=1.0.0
Provides-Extra: dev
Requires-Dist: black==24.10.0; extra == 'dev'
Requires-Dist: mypy==1.11.0; extra == 'dev'
Requires-Dist: pre-commit==4.0.1; extra == 'dev'
Requires-Dist: pytest-asyncio==0.24.0; extra == 'dev'
Requires-Dist: pytest-cov==6.0.0; extra == 'dev'
Requires-Dist: pytest==8.3.0; extra == 'dev'
Requires-Dist: ruff==0.7.0; extra == 'dev'
Provides-Extra: release
Requires-Dist: build==1.0.3; extra == 'release'
Requires-Dist: twine==4.0.2; extra == 'release'
